less/__init__.py
less_version/__init__.py
tests/__init__.py
tests/test_dummy.py
less-0.0.1.dist-info/LICENSE
less-0.0.1.dist-info/METADATA
less-0.0.1.dist-info/WHEEL
less-0.0.1.dist-info/top_level.txt
less-0.0.1.dist-info/RECORD
