Metadata-Version: 2.1
Name: less
Version: 0.0.1
Summary: Interfaceless framework for python
Home-page: http://github.com/fugue-project/less
Author: Han Wang
Author-email: goodwanghan@gmail.com
License: Apache-2.0
Keywords: interfaceless
Platform: UNKNOWN
Classifier: Development Status :: 3 - Alpha
Classifier: Intended Audience :: Developers
Classifier: Topic :: Software Development :: Libraries :: Python Modules
Classifier: License :: OSI Approved :: Apache Software License
Classifier: Programming Language :: Python :: 3.6
Classifier: Programming Language :: Python :: 3.7
Classifier: Programming Language :: Python :: 3.8
Classifier: Programming Language :: Python :: 3 :: Only
Requires-Python: >=3.6
Requires-Dist: triad (>=0.5.0)
